{
  "best_global_step": 4000,
  "best_metric": 0.9422434568405151,
  "best_model_checkpoint": "/home/ubuntu/CS231N/outputs/checkpoint-4000",
  "epoch": 0.8541533205210335,
  "eval_steps": 1000,
  "global_step": 4000,
  "is_hyper_param_search": false,
  "is_local_process_zero": true,
  "is_world_process_zero": true,
  "log_history": [
    {
      "epoch": 0.021353833013025837,
      "grad_norm": 0.9803051948547363,
      "learning_rate": 4.8942985265855224e-05,
      "loss": 0.4763,
      "step": 100
    },
    {
      "epoch": 0.04270766602605167,
      "grad_norm": 1.628197431564331,
      "learning_rate": 4.787529361520393e-05,
      "loss": 0.3098,
      "step": 200
    },
    {
      "epoch": 0.06406149903907751,
      "grad_norm": 3.0544581413269043,
      "learning_rate": 4.680760196455264e-05,
      "loss": 0.2671,
      "step": 300
    },
    {
      "epoch": 0.08541533205210335,
      "grad_norm": 0.9966850876808167,
      "learning_rate": 4.573991031390134e-05,
      "loss": 0.2453,
      "step": 400
    },
    {
      "epoch": 0.10676916506512919,
      "grad_norm": 1.5724879503250122,
      "learning_rate": 4.467221866325005e-05,
      "loss": 0.2287,
      "step": 500
    },
    {
      "epoch": 0.12812299807815503,
      "grad_norm": 1.938642144203186,
      "learning_rate": 4.360452701259876e-05,
      "loss": 0.218,
      "step": 600
    },
    {
      "epoch": 0.14947683109118087,
      "grad_norm": 1.8179290294647217,
      "learning_rate": 4.253683536194747e-05,
      "loss": 0.2115,
      "step": 700
    },
    {
      "epoch": 0.1708306641042067,
      "grad_norm": 0.6874701976776123,
      "learning_rate": 4.1469143711296185e-05,
      "loss": 0.2002,
      "step": 800
    },
    {
      "epoch": 0.19218449711723254,
      "grad_norm": 1.37786865234375,
      "learning_rate": 4.040145206064489e-05,
      "loss": 0.1987,
      "step": 900
    },
    {
      "epoch": 0.21353833013025839,
      "grad_norm": 1.2242521047592163,
      "learning_rate": 3.9333760409993596e-05,
      "loss": 0.1901,
      "step": 1000
    },
    {
      "epoch": 0.21353833013025839,
      "eval_accuracy": 0.9266920685768127,
      "eval_f1": 0.9266920685768127,
      "eval_iou": 0.8397076725959778,
      "eval_loss": 0.17480234801769257,
      "eval_runtime": 107.6098,
      "eval_samples_per_second": 18.325,
      "eval_steps_per_second": 9.163,
      "step": 1000
    },
    {
      "epoch": 0.23489216314328423,
      "grad_norm": 0.82927006483078,
      "learning_rate": 3.8266068759342305e-05,
      "loss": 0.184,
      "step": 1100
    },
    {
      "epoch": 0.25624599615631005,
      "grad_norm": 2.1385841369628906,
      "learning_rate": 3.7198377108691014e-05,
      "loss": 0.1857,
      "step": 1200
    },
    {
      "epoch": 0.2775998291693359,
      "grad_norm": 1.1893202066421509,
      "learning_rate": 3.613068545803972e-05,
      "loss": 0.182,
      "step": 1300
    },
    {
      "epoch": 0.29895366218236175,
      "grad_norm": 0.854081928730011,
      "learning_rate": 3.506299380738843e-05,
      "loss": 0.179,
      "step": 1400
    },
    {
      "epoch": 0.3203074951953876,
      "grad_norm": 1.0598249435424805,
      "learning_rate": 3.399530215673713e-05,
      "loss": 0.1737,
      "step": 1500
    },
    {
      "epoch": 0.3416613282084134,
      "grad_norm": 0.675369918346405,
      "learning_rate": 3.292761050608584e-05,
      "loss": 0.1749,
      "step": 1600
    },
    {
      "epoch": 0.36301516122143923,
      "grad_norm": 1.383765459060669,
      "learning_rate": 3.185991885543455e-05,
      "loss": 0.168,
      "step": 1700
    },
    {
      "epoch": 0.3843689942344651,
      "grad_norm": 1.771300196647644,
      "learning_rate": 3.079222720478326e-05,
      "loss": 0.1707,
      "step": 1800
    },
    {
      "epoch": 0.4057228272474909,
      "grad_norm": 0.9610213041305542,
      "learning_rate": 2.9724535554131965e-05,
      "loss": 0.1671,
      "step": 1900
    },
    {
      "epoch": 0.42707666026051677,
      "grad_norm": 1.8763129711151123,
      "learning_rate": 2.8656843903480674e-05,
      "loss": 0.1619,
      "step": 2000
    },
    {
      "epoch": 0.42707666026051677,
      "eval_accuracy": 0.9354521632194519,
      "eval_f1": 0.9354521632194519,
      "eval_iou": 0.8580890893936157,
      "eval_loss": 0.15104925632476807,
      "eval_runtime": 104.2311,
      "eval_samples_per_second": 18.92,
      "eval_steps_per_second": 9.46,
      "step": 2000
    },
    {
      "epoch": 0.4484304932735426,
      "grad_norm": 0.805110514163971,
      "learning_rate": 2.7599829169335895e-05,
      "loss": 0.161,
      "step": 2100
    },
    {
      "epoch": 0.46978432628656847,
      "grad_norm": 0.9855428338050842,
      "learning_rate": 2.6532137518684607e-05,
      "loss": 0.1628,
      "step": 2200
    },
    {
      "epoch": 0.49113815929959426,
      "grad_norm": 0.9524993300437927,
      "learning_rate": 2.5464445868033316e-05,
      "loss": 0.1601,
      "step": 2300
    },
    {
      "epoch": 0.5124919923126201,
      "grad_norm": 1.1881192922592163,
      "learning_rate": 2.439675421738202e-05,
      "loss": 0.1563,
      "step": 2400
    },
    {
      "epoch": 0.533845825325646,
      "grad_norm": 0.5217995643615723,
      "learning_rate": 2.332906256673073e-05,
      "loss": 0.1555,
      "step": 2500
    },
    {
      "epoch": 0.5551996583386718,
      "grad_norm": 1.3390966653823853,
      "learning_rate": 2.226137091607944e-05,
      "loss": 0.1593,
      "step": 2600
    },
    {
      "epoch": 0.5765534913516976,
      "grad_norm": 1.0538827180862427,
      "learning_rate": 2.1193679265428144e-05,
      "loss": 0.1555,
      "step": 2700
    },
    {
      "epoch": 0.5979073243647235,
      "grad_norm": 0.5765436887741089,
      "learning_rate": 2.0125987614776853e-05,
      "loss": 0.1535,
      "step": 2800
    },
    {
      "epoch": 0.6192611573777493,
      "grad_norm": 1.327852725982666,
      "learning_rate": 1.9058295964125562e-05,
      "loss": 0.156,
      "step": 2900
    },
    {
      "epoch": 0.6406149903907752,
      "grad_norm": 0.9279500246047974,
      "learning_rate": 1.7990604313474267e-05,
      "loss": 0.151,
      "step": 3000
    },
    {
      "epoch": 0.6406149903907752,
      "eval_accuracy": 0.9399927258491516,
      "eval_f1": 0.9399927854537964,
      "eval_iou": 0.8679288029670715,
      "eval_loss": 0.1389279067516327,
      "eval_runtime": 185.7276,
      "eval_samples_per_second": 10.618,
      "eval_steps_per_second": 5.309,
      "step": 3000
    },
    {
      "epoch": 0.661968823403801,
      "grad_norm": 0.568308413028717,
      "learning_rate": 1.6922912662822976e-05,
      "loss": 0.1475,
      "step": 3100
    },
    {
      "epoch": 0.6833226564168268,
      "grad_norm": 1.1977933645248413,
      "learning_rate": 1.5855221012171685e-05,
      "loss": 0.1522,
      "step": 3200
    },
    {
      "epoch": 0.7046764894298526,
      "grad_norm": 1.6182268857955933,
      "learning_rate": 1.4787529361520394e-05,
      "loss": 0.1492,
      "step": 3300
    },
    {
      "epoch": 0.7260303224428785,
      "grad_norm": 0.7596898078918457,
      "learning_rate": 1.3719837710869103e-05,
      "loss": 0.1499,
      "step": 3400
    },
    {
      "epoch": 0.7473841554559043,
      "grad_norm": 1.0573822259902954,
      "learning_rate": 1.265214606021781e-05,
      "loss": 0.1505,
      "step": 3500
    },
    {
      "epoch": 0.7687379884689302,
      "grad_norm": 1.1126004457473755,
      "learning_rate": 1.1584454409566518e-05,
      "loss": 0.1463,
      "step": 3600
    },
    {
      "epoch": 0.790091821481956,
      "grad_norm": 1.090181827545166,
      "learning_rate": 1.0516762758915226e-05,
      "loss": 0.1476,
      "step": 3700
    },
    {
      "epoch": 0.8114456544949818,
      "grad_norm": 1.2604689598083496,
      "learning_rate": 9.449071108263934e-06,
      "loss": 0.1488,
      "step": 3800
    },
    {
      "epoch": 0.8327994875080077,
      "grad_norm": 0.7591704726219177,
      "learning_rate": 8.381379457612643e-06,
      "loss": 0.1472,
      "step": 3900
    },
    {
      "epoch": 0.8541533205210335,
      "grad_norm": 0.8193246722221375,
      "learning_rate": 7.31368780696135e-06,
      "loss": 0.1466,
      "step": 4000
    },
    {
      "epoch": 0.8541533205210335,
      "eval_accuracy": 0.9422434568405151,
      "eval_f1": 0.9422435164451599,
      "eval_iou": 0.872525691986084,
      "eval_loss": 0.13314026594161987,
      "eval_runtime": 221.3314,
      "eval_samples_per_second": 8.91,
      "eval_steps_per_second": 4.455,
      "step": 4000
    }
  ],
  "logging_steps": 100,
  "max_steps": 4683,
  "num_input_tokens_seen": 0,
  "num_train_epochs": 1,
  "save_steps": 1000,
  "stateful_callbacks": {
    "TrainerControl": {
      "args": {
        "should_epoch_stop": false,
        "should_evaluate": false,
        "should_log": false,
        "should_save": true,
        "should_training_stop": false
      },
      "attributes": {}
    }
  },
  "total_flos": 5.60894576689152e+17,
  "train_batch_size": 8,
  "trial_name": null,
  "trial_params": null
}
